setup.py
map_network_viz/__init__.py
map_network_viz/mapmaker.py
map_network_viz-0.0.10.dist-info/LICENSE
map_network_viz-0.0.10.dist-info/METADATA
map_network_viz-0.0.10.dist-info/WHEEL
map_network_viz-0.0.10.dist-info/top_level.txt
map_network_viz-0.0.10.dist-info/RECORD
