Metadata-Version: 2.1
Name: map-network-viz
Version: 0.0.10
Summary: A small wrapper for visualizing street networks and making artistic maps with OpenStreetMap and Networkx.
Author-email: Sejal Dua <sejaldua@gmail.com>
Project-URL: Homepage, https://github.com/sejaldua/map-network-viz
Project-URL: Issues, https://github.com/sejaldua/map-network-viz/issues
Classifier: Programming Language :: Python :: 3
Classifier: License :: OSI Approved :: MIT License
Classifier: Operating System :: OS Independent
Requires-Python: >=3.8
License-File: LICENSE
Requires-Dist: geopandas
Requires-Dist: geopy
Requires-Dist: matplotlib
Requires-Dist: osmnx >=1.8.0
Requires-Dist: urllib3 <2.0
